runium/__init__.py
runium/constants.py
runium/core.py
runium/util.py
tests/__init__.py
tests/test_runium.py
tests/test_runium_threads.py
tests/test_util.py
runium-0.1.8.dist-info/LICENSE
runium-0.1.8.dist-info/METADATA
runium-0.1.8.dist-info/WHEEL
runium-0.1.8.dist-info/top_level.txt
runium-0.1.8.dist-info/RECORD
