Metadata-Version: 2.1
Name: runium
Version: 0.1.8
Summary: Clean and simple task concurrency for Python.
Home-page: https://github.com/AGTGreg/runium
Author: Grigoris Chatzinikolaou
Author-email: greghatzis@gmail.com
License: MIT
Keywords: concurrecy,asynchonous,tasks,scheduling,scheduler,cron,multiprocessing,multithreading,callbacks,non-blocking
Platform: UNKNOWN
Classifier: Programming Language :: Python
Classifier: Programming Language :: Python :: 3
Classifier: Programming Language :: Python :: 3.5
Classifier: Programming Language :: Python :: 3.6
Classifier: Programming Language :: Python :: 3.7
Classifier: License :: OSI Approved :: MIT License
Classifier: Operating System :: OS Independent
